timeMyScript/__init__.py
timeMyScript/timeMyScript.py
timeMyScript-1.0.2.dist-info/LICENSE.txt
timeMyScript-1.0.2.dist-info/METADATA
timeMyScript-1.0.2.dist-info/WHEEL
timeMyScript-1.0.2.dist-info/top_level.txt
timeMyScript-1.0.2.dist-info/RECORD
