Metadata-Version: 2.1
Name: timeMyScript
Version: 1.0.2
Home-page: https://github.com/DeusAres/timeMyScript
Author: DeusAres
License: MIT
Classifier: Programming Language :: Python :: 3
Classifier: Operating System :: OS Independent
License-File: LICENSE.txt
